CHANGELOG.rst
LICENSE.txt
MANIFEST.in
README.rst
setup.cfg
setup.py
djangocms_wow/__init__.py
djangocms_wow/cms_plugins.py
djangocms_wow/models.py
djangocms_wow/tests.py
djangocms_wow/utils.py
djangocms_wow.egg-info/PKG-INFO
djangocms_wow.egg-info/SOURCES.txt
djangocms_wow.egg-info/dependency_links.txt
djangocms_wow.egg-info/not-zip-safe
djangocms_wow.egg-info/requires.txt
djangocms_wow.egg-info/top_level.txt
djangocms_wow/migrations/0001_initial.py
djangocms_wow/migrations/__init__.py
djangocms_wow/south_migrations/0001_initial.py
djangocms_wow/south_migrations/__init__.py
djangocms_wow/static/djangocms_wow/css/animate.css
djangocms_wow/static/djangocms_wow/js/wow.js
djangocms_wow/templates/djangocms_wow/animation.html
djangocms_wow/templates/djangocms_wow/wow_animation.html